PyNeura/__init__.py
PyNeura/cli.py
PyNeura-0.1.0.dist-info/LICENSE
PyNeura-0.1.0.dist-info/METADATA
PyNeura-0.1.0.dist-info/WHEEL
PyNeura-0.1.0.dist-info/entry_points.txt
PyNeura-0.1.0.dist-info/top_level.txt
PyNeura-0.1.0.dist-info/RECORD
